rf_client/__init__.py
rf_client/event_visitor.py
rf_client/log.py
rf_client/map_wrapper.py
rf_client/matchers.py
rf_client/partial_loading.py
rf_client/rf_client.py
rf_client/tree_wrapper.py
rf_client-1.0.2.dist-info/LICENSE
rf_client-1.0.2.dist-info/METADATA
rf_client-1.0.2.dist-info/WHEEL
rf_client-1.0.2.dist-info/top_level.txt
rf_client-1.0.2.dist-info/RECORD
