Metadata-Version: 2.1
Name: rf-client
Version: 1.0.2
Summary: High level RedForester client
Home-page: https://github.com/RedForester/python_rf_client
Author: Red Forester
Author-email: tech@redforester.com
License: MIT
Platform: UNKNOWN
Classifier: Programming Language :: Python :: 3
Classifier: Development Status :: 3 - Alpha
Classifier: License :: OSI Approved :: MIT License
Requires-Python: >=3.6
Requires-Dist: rf-api-client (~=0.1.0)
Requires-Dist: rf-event-listener (~=0.0.0)
Provides-Extra: dev
Requires-Dist: pytest (~=5.4) ; extra == 'dev'
Requires-Dist: pytest-asyncio (~=0.12) ; extra == 'dev'
Requires-Dist: flake8 (~=3.8) ; extra == 'dev'
